LICENSE.txt
MANIFEST.in
README.rst
setup.py
active_subspaces/__init__.py
active_subspaces/as_integrals.py
active_subspaces/as_optimizers.py
active_subspaces/as_response_surfaces.py
active_subspaces/base.py
active_subspaces/domains.py
active_subspaces/gradients.py
active_subspaces/subspaces.py
active_subspaces.egg-info/PKG-INFO
active_subspaces.egg-info/SOURCES.txt
active_subspaces.egg-info/dependency_links.txt
active_subspaces.egg-info/not-zip-safe
active_subspaces.egg-info/requires.txt
active_subspaces.egg-info/top_level.txt
active_subspaces/qp_solvers/__init__.py
active_subspaces/qp_solvers/cvxopt_solver.py
active_subspaces/qp_solvers/gurobi_solver.py
active_subspaces/qp_solvers/qp_solver.py
active_subspaces/utils/__init__.py
active_subspaces/utils/designs.py
active_subspaces/utils/plotters.py
active_subspaces/utils/quadrature.py
active_subspaces/utils/response_surfaces.py
active_subspaces/utils/simrunners.py
active_subspaces/utils/utils.py