Metadata-Version: 1.1
Name: active-subspaces
Version: 0.1.1
Summary: Tools to apply active subspaces to analyze their models and data.
Home-page: https://github.com/paulcon/active_subspaces
Author: Paul Constantine
Author-email: paul.constantine@mines.edu
License: MIT
Keywords: math mathematics active subspaces
Platform: UNKNOWN
Classifier: Development Status :: 3 - Alpha
Classifier: License :: OSI Approved :: MIT License
Classifier: Programming Language :: Python :: 2.7
Classifier: Intended Audience :: Science/Research
Classifier: Topic :: Scientific/Engineering :: Mathematics
